{"ListaPermessi":[{"Id":"71d7febe-c821-4630-8b73-af5b4b2a1f5a","Nome":"User"},{"Id":"649c183f-ef36-41e6-9927-8a9fab526269","Nome":"Admin"}],"Coins":[{"Id":"fdcbba25-f644-4831-8df6-63075fbfff78","Anno":2002,"Commemorativa":false,"Nome":"Un centesimo","Taglio":0,"Valore":0.01},{"Id":"e0b7b765-7d52-4b24-b527-b30876e5f635","Anno":2002,"Commemorativa":false,"Nome":"Due centesimi","Taglio":1,"Valore":0.02},{"Id":"ce4dbb99-470f-4e8f-bf23-09332a2d5959","Anno":2002,"Commemorativa":false,"Nome":"Cinque centesimi","Taglio":2,"Valore":0.05},{"Id":"00fcafa1-6e04-4525-839e-11f7240c81d0","Anno":2002,"Commemorativa":false,"Nome":"Dieci centesimi","Taglio":3,"Valore":0.1},{"Id":"1f57b46e-54b7-46a2-b1ea-0e07f81f2ca0","Anno":2002,"Commemorativa":false,"Nome":"Venti centesimi","Taglio":4,"Valore":0.2},{"Id":"bfd8b49a-2420-477f-94fb-5eb0df8197da","Anno":2002,"Commemorativa":false,"Nome":"Cinquanta centesimi","Taglio":5,"Valore":0.5},{"Id":"7cd73337-a896-49d4-8b63-c4a2789690c6","Anno":2002,"Commemorativa":false,"Nome":"Un euro","Taglio":6,"Valore":1},{"Id":"24d1c2d1-5ed4-476f-8b0f-85f3586a9793","Anno":2002,"Commemorativa":false,"Nome":"Due euro","Taglio":7,"Valore":2},{"Id":"ec640b8a-e77c-4ec0-85d9-dc5e37325fbd","Anno":2003,"Commemorativa":false,"Nome":"Un centesimo","Taglio":0,"Valore":0.01},{"Id":"9b5736e2-eccb-4218-9eba-47cac149094c","Anno":2003,"Commemorativa":false,"Nome":"Due centesimi","Taglio":1,"Valore":0.02},{"Id":"2d4a78f0-91f3-42fa-8f9c-eeff8e7b50ee","Anno":2003,"Commemorativa":false,"Nome":"Cinque centesimi","Taglio":2,"Valore":0.05},{"Id":"7df0f7f9-9bb8-42b9-ba5b-37d267f43aee","Anno":2003,"Commemorativa":false,"Nome":"Dieci centesimi","Taglio":3,"Valore":0.1},{"Id":"26f697b9-ebe9-4c5a-ba3f-bb4d316ea568","Anno":2003,"Commemorativa":false,"Nome":"Venti centesimi","Taglio":4,"Valore":0.2},{"Id":"82320c6c-a990-4cc6-a115-b68e28e1cdf5","Anno":2003,"Commemorativa":false,"Nome":"Cinquanta centesimi","Taglio":5,"Valore":0.5},{"Id":"8a9cf4ce-133b-41bb-98cc-ab834cec765d","Anno":2003,"Commemorativa":false,"Nome":"Un euro","Taglio":6,"Valore":1},{"Id":"e706be2b-2118-43c6-824c-2cb46d796306","Anno":2003,"Commemorativa":false,"Nome":"Due euro","Taglio":7,"Valore":2},{"Id":"44f682b6-5948-4a7b-af27-bede6247e6aa","Anno":2004,"Commemorativa":false,"Nome":"Un centesimo","Taglio":0,"Valore":0.01},{"Id":"7a3bf1f7-f653-4576-ba20-9b1b7889465c","Anno":2004,"Commemorativa":false,"Nome":"Due centesimi","Taglio":1,"Valore":0.02},{"Id":"0b0d8508-f8b1-4baa-9919-35d47ce39d89","Anno":2004,"Commemorativa":false,"Nome":"Cinque centesimi","Taglio":2,"Valore":0.05},{"Id":"31c6ea9e-c05c-4587-8af3-5d27cebfea65","Anno":2004,"Commemorativa":false,"Nome":"Dieci centesimi","Taglio":3,"Valore":0.1},{"Id":"e45e46c1-58a1-4b73-a1ff-f1c40c2b5c44","Anno":2004,"Commemorativa":false,"Nome":"Venti centesimi","Taglio":4,"Valore":0.2},{"Id":"d2fe0da0-a665-4f82-b834-038b1f44a102","Anno":2004,"Commemorativa":false,"Nome":"Cinquanta centesimi","Taglio":5,"Valore":0.5},{"Id":"cfe00228-ad7d-446f-9957-853c915e01c2","Anno":2004,"Commemorativa":false,"Nome":"Un euro","Taglio":6,"Valore":1},{"Id":"a6348b3b-8272-46be-8a38-db76741dc7a5","Anno":2004,"Commemorativa":false,"Nome":"Due euro","Taglio":7,"Valore":2},{"Id":"a243e2c0-57a3-49c5-a043-38586a95cf25","Anno":2005,"Commemorativa":false,"Nome":"Un centesimo","Taglio":0,"Valore":0.01},{"Id":"72ac23f6-787d-417e-9fa9-b244d772bf6f","Anno":2005,"Commemorativa":false,"Nome":"Due centesimi","Taglio":1,"Valore":0.02},{"Id":"b3753218-5829-4f63-881a-8328dfb40f69","Anno":2005,"Commemorativa":false,"Nome":"Cinque centesimi","Taglio":2,"Valore":0.05},{"Id":"28b9d4a9-582d-4a71-8e73-de86231882e8","Anno":2005,"Commemorativa":false,"Nome":"Dieci centesimi","Taglio":3,"Valore":0.1},{"Id":"b4ef87b7-4d5c-40b2-8966-259d669cf8a5","Anno":2005,"Commemorativa":false,"Nome":"Venti centesimi","Taglio":4,"Valore":0.2},{"Id":"6c3d3485-0118-44fe-8820-86233775afda","Anno":2005,"Commemorativa":false,"Nome":"Cinquanta centesimi","Taglio":5,"Valore":0.5},{"Id":"32c84d8e-a438-4419-9201-ea8746067c8b","Anno":2005,"Commemorativa":false,"Nome":"Un euro","Taglio":6,"Valore":1},{"Id":"afc7ffc1-c091-42d5-b52d-18a794039b14","Anno":2005,"Commemorativa":false,"Nome":"Due euro","Taglio":7,"Valore":2},{"Id":"5636943c-b35c-4cc2-9b1b-4dcde972adb4","Anno":2006,"Commemorativa":false,"Nome":"Un centesimo","Taglio":0,"Valore":0.01},{"Id":"4f6a29d8-b4cb-4a60-82ac-addf29ec5773","Anno":2006,"Commemorativa":false,"Nome":"Due centesimi","Taglio":1,"Valore":0.02},{"Id":"3f311454-9542-4687-bf51-7d77d7ae852e","Anno":2006,"Commemorativa":false,"Nome":"Cinque centesimi","Taglio":2,"Valore":0.05},{"Id":"2572e992-602b-4d3d-b5d8-916900595518","Anno":2006,"Commemorativa":false,"Nome":"Dieci centesimi","Taglio":3,"Valore":0.1},{"Id":"d008d4af-a8ad-4062-b7cd-a4003bfea055","Anno":2006,"Commemorativa":false,"Nome":"Venti centesimi","Taglio":4,"Valore":0.2},{"Id":"8a5e6ea2-a210-4b41-aa9e-8766c5fc812a","Anno":2006,"Commemorativa":false,"Nome":"Cinquanta centesimi","Taglio":5,"Valore":0.5},{"Id":"211a9b65-65b6-4b9c-9466-361c68da4f40","Anno":2006,"Commemorativa":false,"Nome":"Un euro","Taglio":6,"Valore":1},{"Id":"d11ea6cf-f1b4-4cff-b350-27bff1f0e293","Anno":2006,"Commemorativa":false,"Nome":"Due euro","Taglio":7,"Valore":2},{"Id":"f14c6e07-c040-4ad1-bfd1-8f1f0238c751","Anno":2007,"Commemorativa":false,"Nome":"Un centesimo","Taglio":0,"Valore":0.01},{"Id":"4fd45a57-2c35-460d-86b5-20ac864925fd","Anno":2007,"Commemorativa":false,"Nome":"Due centesimi","Taglio":1,"Valore":0.02},{"Id":"ba5130ee-4716-4ec4-a0f6-fe78f73b5db1","Anno":2007,"Commemorativa":false,"Nome":"Cinque centesimi","Taglio":2,"Valore":0.05},{"Id":"10c8c09b-3f86-49aa-9274-03956fa545f0","Anno":2007,"Commemorativa":false,"Nome":"Dieci centesimi","Taglio":3,"Valore":0.1},{"Id":"870e4b78-7e8e-4ba5-a908-e37bfe0d7507","Anno":2007,"Commemorativa":false,"Nome":"Venti centesimi","Taglio":4,"Valore":0.2},{"Id":"9e4474d2-b8c1-483e-ba61-a3ebc573757c","Anno":2007,"Commemorativa":false,"Nome":"Cinquanta centesimi","Taglio":5,"Valore":0.5},{"Id":"b1897c2b-2b46-4035-acb0-9f3409be5a5c","Anno":2007,"Commemorativa":false,"Nome":"Un euro","Taglio":6,"Valore":1},{"Id":"f0aed4e5-e51c-4a75-a120-8a7d1fa5e42a","Anno":2007,"Commemorativa":false,"Nome":"Due euro","Taglio":7,"Valore":2},{"Id":"3c04088e-3c2a-4dc0-abf7-879b98bd71a3","Anno":2008,"Commemorativa":false,"Nome":"Un centesimo","Taglio":0,"Valore":0.01},{"Id":"85e8af8b-126f-4af8-a710-e80bb07b56ba","Anno":2008,"Commemorativa":false,"Nome":"Due centesimi","Taglio":1,"Valore":0.02},{"Id":"3ea677b2-309b-48e4-8563-9bcb9c29fb41","Anno":2008,"Commemorativa":false,"Nome":"Cinque centesimi","Taglio":2,"Valore":0.05},{"Id":"9eaa71b0-af25-417d-a076-4b4824426987","Anno":2008,"Commemorativa":false,"Nome":"Dieci centesimi","Taglio":3,"Valore":0.1},{"Id":"ff41fabd-f86f-47e7-9aee-a770482ec765","Anno":2008,"Commemorativa":false,"Nome":"Venti centesimi","Taglio":4,"Valore":0.2},{"Id":"4808f7ed-2250-4c75-b67b-8cb63c146d13","Anno":2008,"Commemorativa":false,"Nome":"Cinquanta centesimi","Taglio":5,"Valore":0.5},{"Id":"95b05181-f6ca-4611-a843-5acc1597d4d0","Anno":2008,"Commemorativa":false,"Nome":"Un euro","Taglio":6,"Valore":1},{"Id":"3afb7a35-ec96-4e45-b9ca-c2dae0301a81","Anno":2008,"Commemorativa":false,"Nome":"Due euro","Taglio":7,"Valore":2},{"Id":"7e813fe0-a359-4895-b6c3-2d81b3161fe8","Anno":2009,"Commemorativa":false,"Nome":"Un centesimo","Taglio":0,"Valore":0.01},{"Id":"894e0b2d-ff74-4f2d-9458-b966ae21c477","Anno":2009,"Commemorativa":false,"Nome":"Due centesimi","Taglio":1,"Valore":0.02},{"Id":"9ebc36da-8407-4a67-a904-ae007c1da63f","Anno":2009,"Commemorativa":false,"Nome":"Cinque centesimi","Taglio":2,"Valore":0.05},{"Id":"6c7d5b4f-9a1f-41eb-af97-5e2aac442018","Anno":2009,"Commemorativa":false,"Nome":"Dieci centesimi","Taglio":3,"Valore":0.1},{"Id":"56af0637-ab7d-45e6-b31c-8c8c6bdf4607","Anno":2009,"Commemorativa":false,"Nome":"Venti centesimi","Taglio":4,"Valore":0.2},{"Id":"10b40dc0-af5a-44fd-8269-0228084d505a","Anno":2009,"Commemorativa":false,"Nome":"Cinquanta centesimi","Taglio":5,"Valore":0.5},{"Id":"ac80b919-468b-4c4e-b644-e01426d753e0","Anno":2009,"Commemorativa":false,"Nome":"Un euro","Taglio":6,"Valore":1},{"Id":"49683bfb-0209-4a69-bed1-45801654ec4e","Anno":2009,"Commemorativa":false,"Nome":"Due euro","Taglio":7,"Valore":2},{"Id":"e40eaeca-aa79-4d2b-a2c0-f64c9e7cea8e","Anno":2010,"Commemorativa":false,"Nome":"Un centesimo","Taglio":0,"Valore":0.01},{"Id":"2620a619-e43d-4aeb-b8a1-8cfd18b5371e","Anno":2010,"Commemorativa":false,"Nome":"Due centesimi","Taglio":1,"Valore":0.02},{"Id":"45f0e1ff-c8ad-4434-abb0-4f67d4a91e64","Anno":2010,"Commemorativa":false,"Nome":"Cinque centesimi","Taglio":2,"Valore":0.05},{"Id":"a0d41967-c5e9-4379-9564-8f2bd6a159da","Anno":2010,"Commemorativa":false,"Nome":"Dieci centesimi","Taglio":3,"Valore":0.1},{"Id":"d2a2ec24-ef60-4e60-bdc8-6dd5eacd0a8b","Anno":2010,"Commemorativa":false,"Nome":"Venti centesimi","Taglio":4,"Valore":0.2},{"Id":"a54ee2f4-5f4a-4047-a373-7f4948498693","Anno":2010,"Commemorativa":false,"Nome":"Cinquanta centesimi","Taglio":5,"Valore":0.5},{"Id":"f9b05d84-d862-4a98-9395-69b69013a748","Anno":2010,"Commemorativa":false,"Nome":"Un euro","Taglio":6,"Valore":1},{"Id":"d85cc85c-aa9f-4ef5-b2af-c70032212ebe","Anno":2010,"Commemorativa":false,"Nome":"Due euro","Taglio":7,"Valore":2},{"Id":"2e479893-2c22-4dde-b87a-674c8e358f66","Anno":2011,"Commemorativa":false,"Nome":"Un centesimo","Taglio":0,"Valore":0.01},{"Id":"000b1f95-ba67-4f01-a0be-55784745bee1","Anno":2011,"Commemorativa":false,"Nome":"Due centesimi","Taglio":1,"Valore":0.02},{"Id":"ee6495e6-3bd4-4094-8b1f-d451327a2240","Anno":2011,"Commemorativa":false,"Nome":"Cinque centesimi","Taglio":2,"Valore":0.05},{"Id":"8ba134a9-2ee3-4a73-acb3-b695bc9fdcba","Anno":2011,"Commemorativa":false,"Nome":"Dieci centesimi","Taglio":3,"Valore":0.1},{"Id":"4f274b43-27f2-4928-8911-47485af3428f","Anno":2011,"Commemorativa":false,"Nome":"Venti centesimi","Taglio":4,"Valore":0.2},{"Id":"08c5f021-4ff7-4ed7-89e4-e7309fcccb38","Anno":2011,"Commemorativa":false,"Nome":"Cinquanta centesimi","Taglio":5,"Valore":0.5},{"Id":"1098a857-742b-4772-b8af-794da6707785","Anno":2011,"Commemorativa":false,"Nome":"Un euro","Taglio":6,"Valore":1},{"Id":"4b6295c5-5d8b-4ead-ae1b-7abfccd20daa","Anno":2011,"Commemorativa":false,"Nome":"Due euro","Taglio":7,"Valore":2},{"Id":"c6006c7f-a444-4aad-9c38-c27b61626f23","Anno":2012,"Commemorativa":false,"Nome":"Un centesimo","Taglio":0,"Valore":0.01},{"Id":"d1f8a741-e7af-4e03-84b6-36f541acb8aa","Anno":2012,"Commemorativa":false,"Nome":"Due centesimi","Taglio":1,"Valore":0.02},{"Id":"3db400a2-7685-47ab-a976-7fa73d50f286","Anno":2012,"Commemorativa":false,"Nome":"Cinque centesimi","Taglio":2,"Valore":0.05},{"Id":"152a4332-a719-49cf-bdca-e96af9081945","Anno":2012,"Commemorativa":false,"Nome":"Dieci centesimi","Taglio":3,"Valore":0.1},{"Id":"67a6a873-5c15-471d-ad25-7be6c3d84272","Anno":2012,"Commemorativa":false,"Nome":"Venti centesimi","Taglio":4,"Valore":0.2},{"Id":"90fc5840-516f-453c-a9a5-e21a79533d39","Anno":2012,"Commemorativa":false,"Nome":"Cinquanta centesimi","Taglio":5,"Valore":0.5},{"Id":"63b22348-3fce-4c5d-bb49-f4bd0de06e64","Anno":2012,"Commemorativa":false,"Nome":"Un euro","Taglio":6,"Valore":1},{"Id":"68cfd847-7b61-46bd-8c8d-c6b0582cba1f","Anno":2012,"Commemorativa":false,"Nome":"Due euro","Taglio":7,"Valore":2},{"Id":"72cd48ed-3809-43df-a640-15788cbe1f32","Anno":2013,"Commemorativa":false,"Nome":"Un centesimo","Taglio":0,"Valore":0.01},{"Id":"c5eaff33-bbda-4ae8-b9e1-0c17c82c3f05","Anno":2013,"Commemorativa":false,"Nome":"Due centesimi","Taglio":1,"Valore":0.02},{"Id":"eab5dfb1-e70d-4ca4-a7fa-c56600cb1f00","Anno":2013,"Commemorativa":false,"Nome":"Cinque centesimi","Taglio":2,"Valore":0.05},{"Id":"65cc53fa-f117-4e3d-a37d-45b3924e9bf3","Anno":2013,"Commemorativa":false,"Nome":"Dieci centesimi","Taglio":3,"Valore":0.1},{"Id":"89bc9a7d-890e-4df4-ad31-06a81784b818","Anno":2013,"Commemorativa":false,"Nome":"Venti centesimi","Taglio":4,"Valore":0.2},{"Id":"5162f343-1c11-4f56-8d6e-10a78fdc3a9e","Anno":2013,"Commemorativa":false,"Nome":"Cinquanta centesimi","Taglio":5,"Valore":0.5},{"Id":"ef0e58cc-f0b1-4d91-a34c-3373291d7375","Anno":2013,"Commemorativa":false,"Nome":"Un euro","Taglio":6,"Valore":1},{"Id":"908f1494-9c06-4145-9921-aad8f6e9b395","Anno":2013,"Commemorativa":false,"Nome":"Due euro","Taglio":7,"Valore":2},{"Id":"15b170bd-c63c-4983-bd3a-8b0f38235f47","Anno":2014,"Commemorativa":false,"Nome":"Un centesimo","Taglio":0,"Valore":0.01},{"Id":"7bc201ec-d004-4a83-addc-bc5155fd66f8","Anno":2014,"Commemorativa":false,"Nome":"Due centesimi","Taglio":1,"Valore":0.02},{"Id":"368f2b54-d1c2-46b8-bf85-6cfb65d4842b","Anno":2014,"Commemorativa":false,"Nome":"Cinque centesimi","Taglio":2,"Valore":0.05},{"Id":"8917db52-aa34-4468-8c84-e83c3486033e","Anno":2014,"Commemorativa":false,"Nome":"Dieci centesimi","Taglio":3,"Valore":0.1},{"Id":"f518e957-b07e-4332-b333-2c05dd353194","Anno":2014,"Commemorativa":false,"Nome":"Venti centesimi","Taglio":4,"Valore":0.2},{"Id":"73022958-1bcb-471d-8148-bb84513a4663","Anno":2014,"Commemorativa":false,"Nome":"Cinquanta centesimi","Taglio":5,"Valore":0.5},{"Id":"4f8d1721-afcb-4f01-aceb-e8aeb30a4ffc","Anno":2014,"Commemorativa":false,"Nome":"Un euro","Taglio":6,"Valore":1},{"Id":"c3e2822d-9d14-4bae-a983-b358cdadb512","Anno":2014,"Commemorativa":false,"Nome":"Due euro","Taglio":7,"Valore":2},{"Id":"20655ccb-22ae-4ffa-81ba-4a0352775a2c","Anno":2015,"Commemorativa":false,"Nome":"Un centesimo","Taglio":0,"Valore":0.01},{"Id":"fea1373f-65d0-4a99-88c4-156db9392659","Anno":2015,"Commemorativa":false,"Nome":"Due centesimi","Taglio":1,"Valore":0.02},{"Id":"6bec6124-7350-4525-9f28-545d44b8426c","Anno":2015,"Commemorativa":false,"Nome":"Cinque centesimi","Taglio":2,"Valore":0.05},{"Id":"0b527c00-b82c-4cf8-abbc-e0c7c296cc0e","Anno":2015,"Commemorativa":false,"Nome":"Dieci centesimi","Taglio":3,"Valore":0.1},{"Id":"a5fbe408-eaa2-4cd0-8747-0a32eade4999","Anno":2015,"Commemorativa":false,"Nome":"Venti centesimi","Taglio":4,"Valore":0.2},{"Id":"d1b300b1-eab1-498a-878e-992b1bf53985","Anno":2015,"Commemorativa":false,"Nome":"Cinquanta centesimi","Taglio":5,"Valore":0.5},{"Id":"93921c44-b2a8-4a5f-9ca2-585d47bdc892","Anno":2015,"Commemorativa":false,"Nome":"Un euro","Taglio":6,"Valore":1},{"Id":"92decd1f-0d61-4cf6-9738-107b082327be","Anno":2015,"Commemorativa":false,"Nome":"Due euro","Taglio":7,"Valore":2},{"Id":"b757523c-f312-436a-be5f-10a351db9b64","Anno":2016,"Commemorativa":false,"Nome":"Un centesimo","Taglio":0,"Valore":0.01},{"Id":"11f66dab-63b9-4a55-8aeb-8d130642b861","Anno":2016,"Commemorativa":false,"Nome":"Due centesimi","Taglio":1,"Valore":0.02},{"Id":"59c3b713-7639-4f8d-83af-5b78d1a5a13e","Anno":2016,"Commemorativa":false,"Nome":"Cinque centesimi","Taglio":2,"Valore":0.05},{"Id":"567bcfcd-b53c-487e-aca3-8d7a8fdccc65","Anno":2016,"Commemorativa":false,"Nome":"Dieci centesimi","Taglio":3,"Valore":0.1},{"Id":"1ace4f21-f2e6-49dc-8ba9-28de5df7913f","Anno":2016,"Commemorativa":false,"Nome":"Venti centesimi","Taglio":4,"Valore":0.2},{"Id":"714bd75a-8295-46bd-bc99-82d930323cee","Anno":2016,"Commemorativa":false,"Nome":"Cinquanta centesimi","Taglio":5,"Valore":0.5},{"Id":"d4c232d5-d045-4403-a271-18f92f3ff499","Anno":2016,"Commemorativa":false,"Nome":"Un euro","Taglio":6,"Valore":1},{"Id":"1a468b04-28a1-4991-9d3a-f012d0f2680b","Anno":2016,"Commemorativa":false,"Nome":"Due euro","Taglio":7,"Valore":2},{"Id":"d959c9ce-b81d-4f6f-8219-ab9d81eb5290","Anno":2017,"Commemorativa":false,"Nome":"Un centesimo","Taglio":0,"Valore":0.01},{"Id":"e7788fd9-0e20-4e91-abbc-a9f524e6f132","Anno":2017,"Commemorativa":false,"Nome":"Due centesimi","Taglio":1,"Valore":0.02},{"Id":"82ecbaf9-4ef5-4766-98b9-2a439cb6905c","Anno":2017,"Commemorativa":false,"Nome":"Cinque centesimi","Taglio":2,"Valore":0.05},{"Id":"4e7332f1-d37b-443c-a30a-76a6941abc97","Anno":2017,"Commemorativa":false,"Nome":"Dieci centesimi","Taglio":3,"Valore":0.1},{"Id":"b09f6039-dddb-45b7-a5ff-162cf6ca8b8e","Anno":2017,"Commemorativa":false,"Nome":"Venti centesimi","Taglio":4,"Valore":0.2},{"Id":"53be4cbd-6b02-4c7f-8796-5273590f47e0","Anno":2017,"Commemorativa":false,"Nome":"Cinquanta centesimi","Taglio":5,"Valore":0.5},{"Id":"9846679a-7277-4ee6-8936-7fae91e3c3b8","Anno":2017,"Commemorativa":false,"Nome":"Un euro","Taglio":6,"Valore":1},{"Id":"3f420d07-aeaa-4914-91ad-78c2dd890e9d","Anno":2017,"Commemorativa":false,"Nome":"Due euro","Taglio":7,"Valore":2},{"Id":"706d1643-dc16-4e55-8325-fbd2b23e84f7","Anno":2018,"Commemorativa":false,"Nome":"Un centesimo","Taglio":0,"Valore":0.01},{"Id":"0829ffd8-6339-457c-9935-a688de898963","Anno":2018,"Commemorativa":false,"Nome":"Due centesimi","Taglio":1,"Valore":0.02},{"Id":"6c195a25-aa77-4864-a204-ac580c979544","Anno":2018,"Commemorativa":false,"Nome":"Cinque centesimi","Taglio":2,"Valore":0.05},{"Id":"cc8d37c2-de65-40db-9a7f-9fcf16470e97","Anno":2018,"Commemorativa":false,"Nome":"Dieci centesimi","Taglio":3,"Valore":0.1},{"Id":"07c88f03-8b97-45ab-8d1e-361eeee94e95","Anno":2018,"Commemorativa":false,"Nome":"Venti centesimi","Taglio":4,"Valore":0.2},{"Id":"657d84f0-139e-4dda-9b2a-f39dae0e64f9","Anno":2018,"Commemorativa":false,"Nome":"Cinquanta centesimi","Taglio":5,"Valore":0.5},{"Id":"66feaf6f-809e-4043-8883-1d66c7230ad3","Anno":2018,"Commemorativa":false,"Nome":"Un euro","Taglio":6,"Valore":1},{"Id":"0e449f2f-9845-4bd7-8fad-bceac68b4458","Anno":2018,"Commemorativa":false,"Nome":"Due euro","Taglio":7,"Valore":2},{"Id":"8fc6a4aa-618f-4cc0-b793-753930ae5a81","Anno":2019,"Commemorativa":false,"Nome":"Un centesimo","Taglio":0,"Valore":0.01},{"Id":"ddba5e3c-87c0-4caa-be2f-26fe1ce52fa8","Anno":2019,"Commemorativa":false,"Nome":"Due centesimi","Taglio":1,"Valore":0.02},{"Id":"1c779b31-8701-4d26-a26f-d74294e9c5dd","Anno":2019,"Commemorativa":false,"Nome":"Cinque centesimi","Taglio":2,"Valore":0.05},{"Id":"532243b8-3499-4723-8c89-b1c3696ade8e","Anno":2019,"Commemorativa":false,"Nome":"Dieci centesimi","Taglio":3,"Valore":0.1},{"Id":"8c32ae26-ed11-434a-a408-52719a328e87","Anno":2019,"Commemorativa":false,"Nome":"Venti centesimi","Taglio":4,"Valore":0.2},{"Id":"0359619f-67e2-4648-8477-f47f12967ae7","Anno":2019,"Commemorativa":false,"Nome":"Cinquanta centesimi","Taglio":5,"Valore":0.5},{"Id":"bccda154-24b9-4e08-a925-640e33d87163","Anno":2019,"Commemorativa":false,"Nome":"Un euro","Taglio":6,"Valore":1},{"Id":"933c0781-3d1f-421c-b209-8ac2d5a58eee","Anno":2019,"Commemorativa":false,"Nome":"Due euro","Taglio":7,"Valore":2},{"Id":"1dac5bc0-18c7-4382-aefb-c6f14cec75e3","Anno":2020,"Commemorativa":false,"Nome":"Un centesimo","Taglio":0,"Valore":0.01},{"Id":"429c67f1-36e7-4d06-88df-eefec58a851c","Anno":2020,"Commemorativa":false,"Nome":"Due centesimi","Taglio":1,"Valore":0.02},{"Id":"3602d6a9-2fc9-482b-b395-8ad06347817b","Anno":2020,"Commemorativa":false,"Nome":"Cinque centesimi","Taglio":2,"Valore":0.05},{"Id":"f72aa6d6-cf3c-4e57-8bb5-680ed286b557","Anno":2020,"Commemorativa":false,"Nome":"Dieci centesimi","Taglio":3,"Valore":0.1},{"Id":"22809657-e630-4f14-972c-96106019f192","Anno":2020,"Commemorativa":false,"Nome":"Venti centesimi","Taglio":4,"Valore":0.2},{"Id":"16a0bc74-9c44-482e-b89e-76dfb75d1817","Anno":2020,"Commemorativa":false,"Nome":"Cinquanta centesimi","Taglio":5,"Valore":0.5},{"Id":"b01c78d9-d4bd-4b62-bf96-2935217d3dd9","Anno":2020,"Commemorativa":false,"Nome":"Un euro","Taglio":6,"Valore":1},{"Id":"4d391b06-08c0-4555-88da-8df6387d2a3f","Anno":2020,"Commemorativa":false,"Nome":"Due euro","Taglio":7,"Valore":2},{"Id":"739dc383-4b94-46b3-a008-ed9d3644f728","Anno":2021,"Commemorativa":false,"Nome":"Un centesimo","Taglio":0,"Valore":0.01},{"Id":"be858d1d-4ee6-43bb-b8ab-d19a587df003","Anno":2021,"Commemorativa":false,"Nome":"Due centesimi","Taglio":1,"Valore":0.02},{"Id":"17202cf4-1762-4102-beca-c98dbd273627","Anno":2021,"Commemorativa":false,"Nome":"Cinque centesimi","Taglio":2,"Valore":0.05},{"Id":"8202cd36-a0b4-4a40-ac48-caea5af2ce5b","Anno":2021,"Commemorativa":false,"Nome":"Dieci centesimi","Taglio":3,"Valore":0.1},{"Id":"16dd86c9-0b38-479b-bcb2-facafb7f0a00","Anno":2021,"Commemorativa":false,"Nome":"Venti centesimi","Taglio":4,"Valore":0.2},{"Id":"55ad61a2-f60e-4c95-a8b5-7de9436baedb","Anno":2021,"Commemorativa":false,"Nome":"Cinquanta centesimi","Taglio":5,"Valore":0.5},{"Id":"903fb854-becf-4e63-b05d-83923b69b06b","Anno":2021,"Commemorativa":false,"Nome":"Un euro","Taglio":6,"Valore":1},{"Id":"ba058132-5b0f-4df8-b242-c77654b2e6e3","Anno":2021,"Commemorativa":false,"Nome":"Due euro","Taglio":7,"Valore":2},{"Id":"d9b5c8ed-e66d-4fbb-aee7-c04bc20f2754","Anno":2022,"Commemorativa":false,"Nome":"Un centesimo","Taglio":0,"Valore":0.01},{"Id":"2b8efa58-67e9-4291-beca-db4fc7710b4c","Anno":2022,"Commemorativa":false,"Nome":"Due centesimi","Taglio":1,"Valore":0.02},{"Id":"4269a812-7d38-41ca-8ac9-2e54f2b32d5a","Anno":2022,"Commemorativa":false,"Nome":"Cinque centesimi","Taglio":2,"Valore":0.05},{"Id":"46cae36c-5f93-4bbb-9721-fe4491d437cf","Anno":2022,"Commemorativa":false,"Nome":"Dieci centesimi","Taglio":3,"Valore":0.1},{"Id":"e6a42a48-025f-4e0e-a0fe-5ddb5dd9a9c6","Anno":2022,"Commemorativa":false,"Nome":"Venti centesimi","Taglio":4,"Valore":0.2},{"Id":"1e9f6994-7385-4aa5-ada3-c3953a9b09f7","Anno":2022,"Commemorativa":false,"Nome":"Cinquanta centesimi","Taglio":5,"Valore":0.5},{"Id":"ed134905-1f0b-4915-a3eb-fb5ec2c20826","Anno":2022,"Commemorativa":false,"Nome":"Un euro","Taglio":6,"Valore":1},{"Id":"7403b1ac-efa0-40d6-8d88-811b126c8d46","Anno":2022,"Commemorativa":false,"Nome":"Due euro","Taglio":7,"Valore":2},{"Id":"f6f55a8c-7783-4a8b-a760-99383d216366","Anno":2023,"Commemorativa":false,"Nome":"Un centesimo","Taglio":0,"Valore":0.01},{"Id":"cb60d807-32c9-451f-9baa-64b994ae8a9d","Anno":2023,"Commemorativa":false,"Nome":"Due centesimi","Taglio":1,"Valore":0.02},{"Id":"d67a1272-18cb-436c-b251-90c1bf591831","Anno":2023,"Commemorativa":false,"Nome":"Cinque centesimi","Taglio":2,"Valore":0.05},{"Id":"12319217-5c91-4eab-a9b2-8d5dac9ab9e4","Anno":2023,"Commemorativa":false,"Nome":"Dieci centesimi","Taglio":3,"Valore":0.1},{"Id":"7fc35bda-861f-46ff-9bff-0fd6ae0e40b0","Anno":2023,"Commemorativa":false,"Nome":"Venti centesimi","Taglio":4,"Valore":0.2},{"Id":"bac65cd6-e352-465f-98a6-20989b230272","Anno":2023,"Commemorativa":false,"Nome":"Cinquanta centesimi","Taglio":5,"Valore":0.5},{"Id":"97aa574d-c13c-4425-a493-2e855b04e902","Anno":2023,"Commemorativa":false,"Nome":"Un euro","Taglio":6,"Valore":1},{"Id":"328157b7-0ee0-4035-bf64-044f26108223","Anno":2023,"Commemorativa":false,"Nome":"Due euro","Taglio":7,"Valore":2},{"Id":"4db3a98e-d99f-4025-bdd4-3d6589f18407","Anno":2024,"Commemorativa":false,"Nome":"Un centesimo","Taglio":0,"Valore":0.01},{"Id":"181d78ec-5a42-4a57-ad96-1e2f3fefa7a5","Anno":2024,"Commemorativa":false,"Nome":"Due centesimi","Taglio":1,"Valore":0.02},{"Id":"8212a159-a14b-4522-b847-32cacfc95050","Anno":2024,"Commemorativa":false,"Nome":"Cinque centesimi","Taglio":2,"Valore":0.05},{"Id":"dfc87a81-cfa5-4485-89bb-08ff2b203d74","Anno":2024,"Commemorativa":false,"Nome":"Dieci centesimi","Taglio":3,"Valore":0.1},{"Id":"83b598c5-a9a1-444c-afe9-e008e9a07ba5","Anno":2024,"Commemorativa":false,"Nome":"Venti centesimi","Taglio":4,"Valore":0.2},{"Id":"c3425c25-e901-4db0-9c03-54c3a13c583f","Anno":2024,"Commemorativa":false,"Nome":"Cinquanta centesimi","Taglio":5,"Valore":0.5},{"Id":"8fa2fe1a-34e8-4879-9d8a-d674d8b036c5","Anno":2024,"Commemorativa":false,"Nome":"Un euro","Taglio":6,"Valore":1},{"Id":"0cab8502-a07c-473b-90e0-3ee0678bacbe","Anno":2024,"Commemorativa":false,"Nome":"Due euro","Taglio":7,"Valore":2},{"Id":"46abc88b-bb6a-428c-b0be-0074395f4b36","Anno":2004,"Commemorativa":true,"Nome":"World Food Programme","Taglio":7,"Valore":2},{"Id":"62e65460-5bcb-4c5f-8463-bec4e6d7d4c0","Anno":2005,"Commemorativa":true,"Nome":"Primo anniversario Costituzione Europea","Taglio":7,"Valore":2},{"Id":"42b3ea73-c0dd-44cc-9bb0-8d30954a3b6a","Anno":2006,"Commemorativa":true,"Nome":"XX Olimpiadi Invernali Torino 2006","Taglio":7,"Valore":2},{"Id":"e52098a3-a841-468b-9ff5-0e5438c167da","Anno":2007,"Commemorativa":true,"Nome":"50\u00B0 anniversario Trattati di Roma","Taglio":7,"Valore":2},{"Id":"eb602365-823f-4561-a106-c82543f93e07","Anno":2008,"Commemorativa":true,"Nome":"60\u00B0 anniversario Dichiarazione Universale dei diritti dell uomo","Taglio":7,"Valore":2},{"Id":"7dc6897a-1ecc-40bb-afc7-6740d51ddfdc","Anno":2009,"Commemorativa":true,"Nome":"200\u00B0 anniversario nascita Louis Braille","Taglio":7,"Valore":2},{"Id":"c41f26b6-176a-455a-a21f-381569d75985","Anno":2009,"Commemorativa":true,"Nome":"10\u00B0 anniversario Unione Economica e Monetaria","Taglio":7,"Valore":2},{"Id":"7e24f8e7-224f-417c-9037-e636bdc8f91c","Anno":2010,"Commemorativa":true,"Nome":"200\u00B0 anniviversario nascita Camillo Benso di Cavour","Taglio":7,"Valore":2},{"Id":"2c6e8382-cd51-47c4-8907-8df548a3aaa9","Anno":2011,"Commemorativa":true,"Nome":"150\u00B0 anniversario Unit\u00E0 d Italia","Taglio":7,"Valore":2},{"Id":"678490b8-7d0d-4515-a888-3c373e8a1002","Anno":2012,"Commemorativa":true,"Nome":"100\u00B0 anniversario morte Giovanni Pascoli","Taglio":7,"Valore":2},{"Id":"bcf1f429-17f2-4d1f-8e3b-1b0614070a6b","Anno":2012,"Commemorativa":true,"Nome":"10 anni di banconote e monete in euro","Taglio":7,"Valore":2},{"Id":"02856a91-cd93-472c-b8d7-22a4e74d1ea5","Anno":2013,"Commemorativa":true,"Nome":"200\u00B0 anniversario nascita di Giuseppe Verdi","Taglio":7,"Valore":2},{"Id":"1fc2aab0-3b7e-416b-a546-c670e781e2db","Anno":2013,"Commemorativa":true,"Nome":"700\u00B0 anniversario nascita Giovanni Boccaccio","Taglio":7,"Valore":2},{"Id":"ab5d2494-4a17-4ba9-afee-003191d36097","Anno":2014,"Commemorativa":true,"Nome":"200\u00B0 anniversario fondazione Arma dei Carabinieri","Taglio":7,"Valore":2},{"Id":"60ae2688-ee08-4196-b7b8-c74b0ce5d3fb","Anno":2014,"Commemorativa":true,"Nome":"450\u00B0 anniversario nascita Galileo Galilei","Taglio":7,"Valore":2},{"Id":"19c23e5a-d54c-49b0-823e-ec8c3aae0194","Anno":2015,"Commemorativa":true,"Nome":"World Expo Milano 2015","Taglio":7,"Valore":2},{"Id":"cc617d5a-ba24-4980-abc1-676cf137ef24","Anno":2015,"Commemorativa":true,"Nome":"750\u00B0 anniversario nascita Dante Alighieri","Taglio":7,"Valore":2},{"Id":"1bd20ae7-7089-41ad-a2fe-e38e9355e5f2","Anno":2015,"Commemorativa":true,"Nome":"30\u00B0 anniversario bandiera europea","Taglio":7,"Valore":2},{"Id":"d74a84d7-7845-4e71-a226-65f5ab9b132d","Anno":2016,"Commemorativa":true,"Nome":"550\u00B0 anniversario morte Donatello","Taglio":7,"Valore":2},{"Id":"06c3ad61-b629-4ecf-8a7c-c57bb4edfd0a","Anno":2016,"Commemorativa":true,"Nome":"2200\u00B0 anniversario morte Tito Maccio Plauto","Taglio":7,"Valore":2},{"Id":"9452fcfc-e683-4f82-9852-f1643ab6e0e0","Anno":2017,"Commemorativa":true,"Nome":"400\u00B0 anniv. completamento basilica di San Marco a Venezia","Taglio":7,"Valore":2},{"Id":"03eaef10-d583-4bef-9bbb-9fc38ef47396","Anno":2017,"Commemorativa":true,"Nome":"2000\u00B0 anniversario morte Tito Livio","Taglio":7,"Valore":2},{"Id":"fc237e8c-4849-4aa9-8d2f-cdec5f83d7f6","Anno":2018,"Commemorativa":true,"Nome":"70\u00B0 anniversario Costituzione Repubblica Italiana","Taglio":7,"Valore":2},{"Id":"b70b9c96-93e3-45eb-945e-dc173be278bc","Anno":2018,"Commemorativa":true,"Nome":"60\u00B0 anniversario Ministero della Salute","Taglio":7,"Valore":2},{"Id":"6b163cf6-c25f-4e71-bd74-e01da769225c","Anno":2019,"Commemorativa":true,"Nome":"500\u00B0 anniversario morte Leonardo da Vinci","Taglio":7,"Valore":2},{"Id":"39aa3067-4f13-4d73-8234-190564b3ec25","Anno":2020,"Commemorativa":true,"Nome":"80\u00B0 anniversario Fondazione Corpo Nazionale dei Vigili del Fuoco","Taglio":7,"Valore":2},{"Id":"fca1c088-c1d9-41b4-92bd-48b9ebcefb8c","Anno":2020,"Commemorativa":true,"Nome":"150\u00BA anniversario nascita Maria Montessori","Taglio":7,"Valore":2},{"Id":"a34b6e6c-49be-4898-ac65-d03eb70afaa6","Anno":2021,"Commemorativa":true,"Nome":"150\u00B0 anniversario Roma Capitale d\u0027Italia","Taglio":7,"Valore":2},{"Id":"d7a2bbc6-0c9f-40f6-96e6-b174c257910f","Anno":2021,"Commemorativa":true,"Nome":"Professioni sanitarie","Taglio":7,"Valore":2},{"Id":"e2905865-3ac3-4b9e-8b28-99c2796c5672","Anno":2022,"Commemorativa":true,"Nome":"170\u00BA anniversario Polizia di Stato","Taglio":7,"Valore":2},{"Id":"e26348ee-175d-47ea-b8e8-b6eb0d4a0abf","Anno":2022,"Commemorativa":true,"Nome":"30\u00BA anniversario morte di Giovanni Falcone e Paolo Borsellino","Taglio":7,"Valore":2},{"Id":"3abadf91-329f-4520-a8b6-f276eb36e244","Anno":2022,"Commemorativa":true,"Nome":"35\u00BA anniversario Programma Erasmus","Taglio":7,"Valore":2},{"Id":"e9f58dfa-15c1-434b-9844-1f53e260041e","Anno":2023,"Commemorativa":true,"Nome":"100\u00B0 anniversario Aeronautica militare","Taglio":7,"Valore":2},{"Id":"f7f6b6e0-db97-47ee-832b-178508d36038","Anno":2023,"Commemorativa":true,"Nome":"150\u00BA anniversario morte Alessandro Manzoni","Taglio":7,"Valore":2},{"Id":"092b3aa3-4cc4-41e3-b113-c048a219705c","Anno":2024,"Commemorativa":true,"Nome":"250\u00B0 anniversario Fondazione Guardia di Finanza","Taglio":7,"Valore":2},{"Id":"a388c8b3-7f51-4c54-80e2-568794fe06aa","Anno":2024,"Commemorativa":true,"Nome":"Rita Levi Montalcini","Taglio":7,"Valore":2}],"Users":[{"Id":"84090e3a-201d-4d33-ae01-f1c12832009c","NickName":"vincenzo","Password":"anteria2024","Coins":[],"Permessi":[{"Id":"71d7febe-c821-4630-8b73-af5b4b2a1f5a","Nome":"User"},{"Id":"649c183f-ef36-41e6-9927-8a9fab526269","Nome":"Admin"}]},{"Id":"6416674f-6d69-4473-bc19-fbfd83aa7850","NickName":"andrea","Password":"si2001","Coins":[],"Permessi":[{"Id":"71d7febe-c821-4630-8b73-af5b4b2a1f5a","Nome":"User"}]}]}